GdbDiaoshiJiaochengCYuyanBianchengWang/README.md
GdbDiaoshiJiaochengCYuyanBianchengWang/__init__.py
GdbDiaoshiJiaochengCYuyanBianchengWang/__main__.py
GdbDiaoshiJiaochengCYuyanBianchengWang/file.epub
GdbDiaoshiJiaochengCYuyanBianchengWang/index.html
GdbDiaoshiJiaochengCYuyanBianchengWang/css/__init__.py
GdbDiaoshiJiaochengCYuyanBianchengWang/css/annotations.css
GdbDiaoshiJiaochengCYuyanBianchengWang/css/main.css
GdbDiaoshiJiaochengCYuyanBianchengWang/css/normalize.css
GdbDiaoshiJiaochengCYuyanBianchengWang/css/popup.css
GdbDiaoshiJiaochengCYuyanBianchengWang/font/__init__.py
GdbDiaoshiJiaochengCYuyanBianchengWang/font/fontello.eot
GdbDiaoshiJiaochengCYuyanBianchengWang/font/fontello.svg
GdbDiaoshiJiaochengCYuyanBianchengWang/font/fontello.ttf
GdbDiaoshiJiaochengCYuyanBianchengWang/font/fontello.woff
GdbDiaoshiJiaochengCYuyanBianchengWang/img/__init__.py
GdbDiaoshiJiaochengCYuyanBianchengWang/img/annotator-glyph-sprite.png
GdbDiaoshiJiaochengCYuyanBianchengWang/img/annotator-icon-sprite.png
GdbDiaoshiJiaochengCYuyanBianchengWang/img/apple-touch-icon.png
GdbDiaoshiJiaochengCYuyanBianchengWang/img/cancelfullscreen.png
GdbDiaoshiJiaochengCYuyanBianchengWang/img/close.png
GdbDiaoshiJiaochengCYuyanBianchengWang/img/fullscreen.png
GdbDiaoshiJiaochengCYuyanBianchengWang/img/loader.gif
GdbDiaoshiJiaochengCYuyanBianchengWang/img/menu-icon.png
GdbDiaoshiJiaochengCYuyanBianchengWang/img/save.png
GdbDiaoshiJiaochengCYuyanBianchengWang/img/saved.png
GdbDiaoshiJiaochengCYuyanBianchengWang/img/settings-s.png
GdbDiaoshiJiaochengCYuyanBianchengWang/img/settings.png
GdbDiaoshiJiaochengCYuyanBianchengWang/img/star.png
GdbDiaoshiJiaochengCYuyanBianchengWang/js/__init__.py
GdbDiaoshiJiaochengCYuyanBianchengWang/js/epub.js
GdbDiaoshiJiaochengCYuyanBianchengWang/js/epub.min.js
GdbDiaoshiJiaochengCYuyanBianchengWang/js/epub.min.map
GdbDiaoshiJiaochengCYuyanBianchengWang/js/hooks.min.js
GdbDiaoshiJiaochengCYuyanBianchengWang/js/hooks.min.map
gdb_diaoshi_jiaocheng_c_yuyan_biancheng_wang-2024.3.4.0.dist-info/METADATA
gdb_diaoshi_jiaocheng_c_yuyan_biancheng_wang-2024.3.4.0.dist-info/WHEEL
gdb_diaoshi_jiaocheng_c_yuyan_biancheng_wang-2024.3.4.0.dist-info/entry_points.txt
gdb_diaoshi_jiaocheng_c_yuyan_biancheng_wang-2024.3.4.0.dist-info/top_level.txt
gdb_diaoshi_jiaocheng_c_yuyan_biancheng_wang-2024.3.4.0.dist-info/RECORD
